fromjs/__init__.py
fromjs/main.py
fromjs-0.1.0.dist-info/METADATA
fromjs-0.1.0.dist-info/WHEEL
fromjs-0.1.0.dist-info/licenses/LICENSE
fromjs-0.1.0.dist-info/RECORD
