Metadata-Version: 2.4
Name: FromJS
Version: 0.1.0
Summary: A Python library for parsing and executing JavaScript code within Python applications.
Project-URL: Homepage, https://github.com/obedienceadara/FromJS
Project-URL: Bug Tracker, https://github.com/obedienceadara/FromJS/issues
Author-email: Obedience Adara <obedienceadara@gmail.com>
License-File: LICENSE
Classifier: License :: OSI Approved :: MIT License
Classifier: Operating System :: OS Independent
Classifier: Programming Language :: Python :: 3
Requires-Python: >=3.7
Requires-Dist: esprima>=4.0.0
